{"cat": "Additional Info", "title": "👴Lindy Effect", "desc": "What is the Lindy Effect?", "msgs": [{"text": "What is the Lindy Effect?"}, {"text": "Lindy Effect \nthe future life expectancy of some non-perishable things, like a technology or an idea, is proportional to their current age\nhttps://fourweekmba.com/lindy-effect/\nhttps://medium.com/@samuelpedro1992/what-is-the-lindy-effect-3c1d6ec96a08", "link": "https://fourweekmba.com/lindy-effect/", "imgs": ["images/helpdesk/lindy_effect_010_lindy_effect_0_z9adxpKh6B4mmFYX.png", "images/helpdesk/lindy_effect_008_lindy-effect.png"]}, {"text": "."}]}